README.md
pyproject.toml
setup.py
omniCLIP/__init__.py
omniCLIP/omniCLIP.py
omniCLIP/data_parsing/CreateGeneAnnotDB.py
omniCLIP/data_parsing/GetCoverageFromBam.py
omniCLIP/data_parsing/LoadReads.py
omniCLIP/data_parsing/ParsingArgs.py
omniCLIP/data_parsing/ParsingPositions.py
omniCLIP/data_parsing/__init__.py
omniCLIP/data_parsing/tools.py
omniCLIP/omni_stat/FitBinoDirchEmmisionProbabilities.py
omniCLIP/omni_stat/__init__.py
omniCLIP/omni_stat/diag_event_model.py
omniCLIP/omni_stat/emission_prob.py
omniCLIP/omni_stat/mixture_tools.py
omniCLIP/omni_stat/multdirichletVect.py
omniCLIP/omni_stat/sparse_glm.py
omniCLIP/omni_stat/trans.py
omniCLIP/omni_stat/utils.py
omniCLIP/omni_stat/viterbi.pyx
omniCLIP_test.egg-info/PKG-INFO
omniCLIP_test.egg-info/SOURCES.txt
omniCLIP_test.egg-info/dependency_links.txt
omniCLIP_test.egg-info/entry_points.txt
omniCLIP_test.egg-info/not-zip-safe
omniCLIP_test.egg-info/requires.txt
omniCLIP_test.egg-info/top_level.txt