Metadata-Version: 2.1
Name: omniCLIP-test
Version: 0.1a9
Summary: Test of the omniCLIP project
Home-page: https://github.com/simojoe/omniCLIP
Author: Philipp Boss
Author-email: joel.simoneau@mdc-berlin.de
License: UNKNOWN
Platform: UNKNOWN
Classifier: Programming Language :: Python :: 3
Classifier: Operating System :: OS Independent
